querynest/__init__.py
querynest/cli/__init__.py
querynest/cli/main.py
querynest/cli/commands/__init__.py
querynest/cli/commands/chat.py
querynest/cli/commands/config.py
querynest/cli/commands/history.py
querynest/cli/commands/sessions.py
querynest/config/__init__.py
querynest/config/bootstrap.py
querynest/config/config_loader.py
querynest/config/config_model.py
querynest/config/gemini.py
querynest/config/setup.py
querynest/embeddings/__init__.py
querynest/embeddings/embedder.py
querynest/loaders/__init__.py
querynest/loaders/pdf_loader.py
querynest/loaders/web_loader.py
querynest/loaders/youtube_loader.py
querynest/memory/__init__.py
querynest/memory/chat_memory.py
querynest/processor/__init__.py
querynest/processor/text_splitter.py
querynest/prompts/__init__.py
querynest/prompts/prompt_template.py
querynest/rag/rag_chain.py
querynest/retriever/__init__.py
querynest/sessions/session_meta.py
querynest/utils/__init__.py
querynest/utils/hashing.py
querynest/utils/paths.py
querynest/vector_store/__init__.py
querynest/vector_store/faiss_store.py
querynest_cli-1.0.2.dist-info/licenses/LICENSE
querynest_cli-1.0.2.dist-info/METADATA
querynest_cli-1.0.2.dist-info/WHEEL
querynest_cli-1.0.2.dist-info/entry_points.txt
querynest_cli-1.0.2.dist-info/top_level.txt
querynest_cli-1.0.2.dist-info/RECORD
