Metadata-Version: 2.4
Name: querynest-cli
Version: 1.0.2
Summary: FAISS-first RAG CLI for documents and web pages
Author: Divyansh Sharma
License:                     GNU GENERAL PUBLIC LICENSE
Keywords: rag,faiss,llm,cli,ai,langchain
Classifier: Development Status :: 3 - Alpha
Classifier: Environment :: Console
Classifier: Intended Audience :: Developers
Classifier: License :: OSI Approved :: GNU General Public License v3 (GPLv3)
Classifier: Programming Language :: Python :: 3
Classifier: Programming Language :: Python :: 3.10
Classifier: Programming Language :: Python :: 3.11
Classifier: Programming Language :: Python :: 3.12
Classifier: Topic :: Scientific/Engineering :: Artificial Intelligence
Classifier: Topic :: Software Development :: Libraries
Requires-Python: >=3.10
License-File: LICENSE
Requires-Dist: langchain<0.4,>=0.3
Requires-Dist: langchain-core<0.4,>=0.3
Requires-Dist: langchain-community<0.4,>=0.3
Requires-Dist: langchain-text-splitters<0.4,>=0.3
Requires-Dist: langchain-google-genai<3.0,>=2.0
Requires-Dist: google-generativeai<1.0,>=0.8
Requires-Dist: python-dotenv>=1.0
Requires-Dist: faiss-cpu<2.0,>=1.7.4
Requires-Dist: tiktoken>=0.6
Requires-Dist: pydantic<3.0,>=2.5
Requires-Dist: pypdf>=4.0
Requires-Dist: requests>=2.31
Requires-Dist: beautifulsoup4>=4.12
Requires-Dist: readability-lxml>=0.8
Requires-Dist: lxml>=5.0
Requires-Dist: lxml-html-clean>=0.1
Requires-Dist: tqdm>=4.66
Requires-Dist: typer>=0.12
Requires-Dist: rich>=13.7
Dynamic: license-file
